qat/anapli/__init__.pyd
qat/anapli/crossing_lattice.pyd
qat/anapli/geometry.pyd
qat/anapli/ising_crossing_lattice.pyd
qat/anapli/mwis_crossing_lattice.pyd
qat/anapli/optimal_layout.pyd
qat/anapli/optimization.pyd
qat/anapli/qubo_crossing_lattice.pyd
qat/anapli/schedule.pyd
qat/anapli/version.pyd
qat_anapli-0.2.0.dist-info/licenses/LICENSE.txt
qat_anapli-0.2.0.dist-info/METADATA
qat_anapli-0.2.0.dist-info/WHEEL
qat_anapli-0.2.0.dist-info/top_level.txt
qat_anapli-0.2.0.dist-info/RECORD
