Metadata-Version: 2.4
Name: qat-anapli
Version: 0.2.0
Summary: Module qat-anapli [7ddccd5] - Compiled by Eviden
Home-page: https://atos.net/en/lp/myqlm
Author: Eviden Quantum Lab
Author-email: myqlm@atos.net
License: Eviden myQLM EULA
Project-URL: Documentation, https://myqlm.github.io
Project-URL: Bug Tracker, https://github.com/myQLM/myqlm-issues/issues
Project-URL: Community, https://myqlmworkspace.slack.com
Keywords: Quantum,myQLM,QLM,Atos,Eviden
Platform: Operating System :: POSIX :: Linux
Classifier: Operating System :: POSIX :: Linux
Classifier: Programming Language :: Python :: 3.9
Classifier: Topic :: Scientific/Engineering
Classifier: License :: Other/Proprietary License
License-File: LICENSE.txt
Requires-Dist: numpy~=2.0
Requires-Dist: matplotlib
Requires-Dist: networkx
Requires-Dist: qat-comm
Requires-Dist: qat-core
Dynamic: author
Dynamic: author-email
Dynamic: classifier
Dynamic: description
Dynamic: description-content-type
Dynamic: home-page
Dynamic: keywords
Dynamic: license
Dynamic: license-file
Dynamic: platform
Dynamic: project-url
Dynamic: requires-dist
Dynamic: summary
